setup.py
LLOneSignal.egg-info/PKG-INFO
LLOneSignal.egg-info/SOURCES.txt
LLOneSignal.egg-info/dependency_links.txt
LLOneSignal.egg-info/not-zip-safe
LLOneSignal.egg-info/top_level.txt
OneSignal/OSConnection.py
OneSignal/OSFilter.py
OneSignal/OSHeader.py
OneSignal/OSOperator.py
OneSignal/OSPayload.py
OneSignal/OSResponse.py
OneSignal/__init__.py