Metadata-Version: 1.0
Name: LLOneSignal
Version: 0.1
Summary: Integracion L&L OneSignal
Home-page: http://github.com/storborg/LLOneSignal
Author: Isodinamia
Author-email: info@isodinamia.com
License: MIT
Platform: UNKNOWN
